{
  "additional_requirements": {
    "forge_tier": 5
  },
  "essences": {
    "aureal": 9000,
    "blood": 5000,
    "experience": 5000,
    "souls": 500
  },
  "inputs": [
    {
      "amount": 1,
      "ingredient": {
        "item": "alexsmobs:void_worm_eye"
      }
    },
    {
      "amount": 1,
      "ingredient": {
        "item": "traveloptics:void_spellweave_ingot"
      }
    },
    {
      "amount": 1,
      "ingredient": {
        "item": "simplyswords:runic_tablet"
      }
    },
    {
      "amount": 1,
      "ingredient": {
        "item": "traveloptics:void_spellweave_ingot"
      }
    },
    {
      "amount": 1,
      "ingredient": {
        "item": "simplyswords:runic_tablet"
      }
    },
    {
      "amount": 1,
      "ingredient": {
        "item": "traveloptics:void_spellweave_ingot"
      }
    },
    {
      "amount": 1,
      "ingredient": {
        "item": "simplyswords:runic_tablet"
      }
    },
    {
      "amount": 1,
      "ingredient": {
        "item": "traveloptics:void_spellweave_ingot"
      }
    }
  ],
  "main_ingredient": {
    "item": "knavesneeds:forbidden_arcanus/draco_arcanus/scythe"
  },
  "magic_circle": {
    "inner_texture": "forbidden_arcanus:textures/effect/magic_circle/inner/origin.png",
    "outer_texture": "forbidden_arcanus:textures/effect/magic_circle/outer/pactum.png"
  },
  "result": {
    "type": "forbidden_arcanus:create_item",
    "result_item": {
      "Count": 1,
      "id": "traveloptics:voidstrike_reaper"
    }
  }
}